deskripsiKelompok2/__init__.py
deskripsiKelompok2/deskripsi.py
DeskripsiKodeKelompok2-0.1.dist-info/LICENSE
DeskripsiKodeKelompok2-0.1.dist-info/METADATA
DeskripsiKodeKelompok2-0.1.dist-info/WHEEL
DeskripsiKodeKelompok2-0.1.dist-info/top_level.txt
DeskripsiKodeKelompok2-0.1.dist-info/RECORD
